respunct/__init__.py
respunct/punct.py
respunct-1.0.0.dist-info/LICENSE
respunct-1.0.0.dist-info/METADATA
respunct-1.0.0.dist-info/WHEEL
respunct-1.0.0.dist-info/top_level.txt
respunct-1.0.0.dist-info/RECORD
