Metadata-Version: 2.1
Name: respunct
Version: 1.0.0
Summary: An easy-to-use package to restore punctuation of portuguese texts.
Home-page: https://github.com/DominguesM/respunct
Author: Maicon Domingues
Author-email: dominguesm@outlook.com
License: Apache Software License
Classifier: Intended Audience :: Science/Research
Classifier: License :: OSI Approved :: Apache Software License
Classifier: Programming Language :: Python :: 3
Classifier: Topic :: Scientific/Engineering :: Artificial Intelligence
Requires-Python: >=3.7
License-File: LICENSE
Requires-Dist: simpletransformers (==0.63.7)
Requires-Dist: torch (==1.12.0)
